setup.py
distributions_memedi_2024/Binomialdistribution.py
distributions_memedi_2024/Gaussiandistribution.py
distributions_memedi_2024/Generaldistribution.py
distributions_memedi_2024/__init__.py
distributions_memedi_2024.egg-info/PKG-INFO
distributions_memedi_2024.egg-info/SOURCES.txt
distributions_memedi_2024.egg-info/dependency_links.txt
distributions_memedi_2024.egg-info/not-zip-safe
distributions_memedi_2024.egg-info/top_level.txt